ycfuncs/__init__.py
ycfuncs/main.py
ycfuncs-25.8.81530.dist-info/METADATA
ycfuncs-25.8.81530.dist-info/WHEEL
ycfuncs-25.8.81530.dist-info/RECORD
