Metadata-Version: 2.4
Name: ycfuncs
Version: 25.8.81530
Summary: Handler for FastAPI apps in Yandex Cloud Functions
Author-email: RA <root.of.system@gmail.com>
Requires-Python: >=3.12
Requires-Dist: fastapi[standard]>=0.116.1
